{"name": "blink-182", "genre": "Pop/Rock", "albums": ["Buddha", "Cheshire Cat", "Greatest Hits", "Nine", "Neighborhoods", "Enema of the State"], "similars": ["All Time Low", "Allister", "Green Day", "MxPx", "NOFX", "Simple Plan", "Sum 41", "Unwritten Law", "Face to Face", "Goldfinger", "Good Charlotte", "New Found Glory", "Pennywise", "Save Ferris", "Strung Out", "The Bouncing Souls", "The Offspring", "The Suicide Machines", "Alkaline Trio", "Dillinger Four", "Fenix TX", "Home Grown", "Lit", "Me First and the Gimme Gimmes", "Mercury", "Millencolin", "Neck Deep", "Operation Ivy", "Roam", "Saves the Day", "Slack Season", "Sunrise Skater Kids", "Symposium", "Taking Back Sunday", "The All-American Rejects", "The Manges", "The Matches", "Amazing Transparent Man", "Bloodhound Gang", "Bowling for Soup", "Buck-O-Nine", "Busted", "Flashlight Brown", "Lagwagon", "Less Than Jake", "Midtown", "Motion City Soundtrack", "No Motiv", "Plain White T's", "The Queers", "Uptown Sinclair", "Fall Out Boy", "Goo Goo Dolls", "Milestones", "Nada Surf", "No Doubt", "One OK Rock", "Paramore", "Rancid", "Reel Big Fish", "The Get Up Kids", "The Madden Brothers"], "influencers": ["All", "Descendents", "NOFX", "The Offspring", "Adolescents", "Down by Law", "Face to Face", "Green Day", "Nirvana", "Operation Ivy", "Pansy Division", "Pennywise", "Rancid", "The Mr. T Experience", "The Vandals", "Agent Orange", "Bad Religion", "Circle Jerks", "Generation X", "Ramones", "Screeching Weasel", "Dead Milkmen"], "followers": ["Good Charlotte", "New Found Glory", "Paramore", "Plain White T's", "Simple Plan", "The All-American Rejects", "Avril Lavigne", "Boys Like Girls", "Cute Is What We Aim For", "Forever the Sickest Kids", "Harvey Danger", "Motion City Soundtrack", "Panic! At the Disco", "Relient K", "The Red Jumpsuit Apparatus", "The White Tie Affair", "All Time Low", "Anberlin", "Biffy Clyro", "Hey Monday", "Jonas Brothers", "McFly", "Picasso Jones", "Push Play", "The Maine", "A Day to Remember", "Allstar Weekend", "Bayside", "In Her Own Words", "Madina Lake", "Noogie", "Backwordz", "Coffin Carousel", "COUNTERFEIT.", "Fat Nick", "Forfun", "Goody Grace", "Half the Animal", "Hundred Handed", "Juice WRLD", "LILHUDDY", "Machine Gun Kelly", "Michael Constantino", "Neck Deep", "Paris Shadows", "Roam", "Save the Lost Boys", "State Champs", "Terence Ryan", "Travis Mills", "Two Friends", "White Eskimo", "With Confidence"]}