{"name": "The Beach Boys", "genre": "Pop/Rock", "albums": ["Surf's Up", "Sunflower", "Summer Days (And Summer Nights!!)", "Sounds of Summer: The Very Best of the Beach Boys", "Smiley Smile", "In Concert"], "similars": ["The Beatles", "The Four Seasons", "The Mamas & the Papas", "The Turtles", "Fleetwood Mac", "Jan & Dean", "Sagittarius", "The Association", "The Grass Roots", "The Hollies", "The Lovin' Spoonful", "The Monkees", "The Zombies", "Boyce & Hart", "Boys Next Door", "Chicago", "Curt Boettcher", "Gary Usher", "Harry Nilsson", "Love", "Mortimer", "Roger Nichols", "Roy Wood", "The Bel-Airs", "The First Class", "The Free Design", "The Left Banke", "The Millennium", "The Raspberries", "The Shirelles", "The Sundowners", "The Sunrays", "The Tokens", "Tommy James & the Shondells", "Yellow Balloon", "America", "Brute Force", "City Surfers", "Dick Dale", "Gerry & the Pacemakers", "Original Surfaris", "Orpheus", "Richie Allen", "Sandy Salisbury", "The Astronauts", "The Atlantics", "The Challengers", "The Chantays", "The Cornells", "The Fantastic Baggys", "The Kickstands", "The Lively Ones", "The Premiers", "The Revells", "The Rip Chords", "The Rivieras", "The Super Stocks", "The Surfaris", "The Ventures", "Donovan", "Frankie Valli", "Jimmy Buffett"], "influencers": ["Chuck Berry", "Phil Spector", "The Four Freshmen", "The Everly Brothers", "Buddy Holly", "Chubby Checker", "Dion", "Frankie Lymon", "Ray Conniff", "The Beatles", "The Four Preps", "The Four Seasons", "The Hi-Lo's", "Duane Eddy", "The Platters"], "followers": ["Cheap Trick", "Emitt Rhodes", "Jan & Dean", "Roy Wood", "The High Llamas", "The Raspberries", "The Wondermints", "ABBA", "Air", "Big Star", "Billy Nicholls", "Carpenters", "Chicago", "Fleetwood Mac", "Neutral Milk Hotel", "Sagittarius", "The Association", "The Dukes of Stratosphear", "The Left Banke", "The Mamas & the Papas", "The Millennium", "The Move", "The Neon Philharmonic", "The Turtles", "Todd Rundgren", "XTC", "Yellow Balloon", "Alan Menken", "BMX Bandits", "Bread", "Cardinal", "Crosby, Stills & Nash", "Dwight Twilley", "Fleet Foxes", "Fountains of Wayne", "Frank Black", "Gorky's Zygotic Mynci", "Herb Alpert", "Jellyfish", "Lindsey Buckingham", "Marshall Crenshaw", "Matthew Sweet", "My Bloody Valentine", "Panic! At the Disco", "Pixies", "R.E.M.", "Ron Sexsmith", "Saint Etienne", "Sean Lennon", "Simian", "Sondre Lerche", "The Apples in Stereo", "The Brother Brothers", "The Ivy League", "The Ladybug Transistor", "The Olivia Tremor Control", "The Pernice Brothers", "The Plimsouls", "Velvet Crush", "Yo La Tengo", "Animal Collective", "Ashe", "Cornelius", "Harry Nilsson", "Ramones", "Stereolab", "The Boys with Perpetual Nervousness", "The dB's", "Utopia", "Zumpano", "Bikeride", "Birds of Tokyo", "B\u00d8RNS", "Color Bars", "Husky", "Kings of Convenience", "Mo Troper", "Once & Future Band", "Phil Ajjarapu", "Pugwash", "Summer Fiction", "Summer Salt", "Sweet Baboo", "Teleman", "That Poppy", "The Aluminum Group", "The Aquadolls", "The Blue Jean Committee", "The Butterscotch Cathedral", "The Hoof & the Heel", "The Just Joans", "The Legal Matters", "The Lemon Twigs", "Tom Wardle", "Treefight for Sunlight", "Violet Days", "We Are Catchers", "Weezer"]}