{"name": "The Animals", "genre": "Pop/Rock", "albums": ["Animalisms", "Absolute Animals 1964-1968", "Animal Tracks [UK]", "Before We Were So Rudely Interrupted", "Animalization", "The Animals [US]"], "similars": ["The Rolling Stones", "The Yardbirds", "Them", "Alexis Korner", "Cyril Davies", "Q 65", "Small Faces", "The Belfast Gypsies", "The Pretty Things", "The Troggs", "Georgie Fame", "Manfred Mann", "The Dave Clark Five", "The Kinks", "The V.I.P.s", "The Who", "Wayne Fontana and the Mindbenders", "Bob Seger", "David Johansen", "Electric Banana", "Jefferson Airplane", "Jimi Hendrix", "John Lennon", "New York Dolls", "Animals II", "Brian Auger", "Brownsville Station", "Eric Clapton", "The Byrds", "The Honeydrippers"], "influencers": ["Bo Diddley", "Chuck Berry", "Jimmy Reed", "John Lee Hooker", "Muddy Waters", "Sonny Boy Williamson II", "Bob Dylan", "Sam Cooke", "The Beatles", "Big Joe Turner", "Buddy Guy", "Elmore James", "Elvis Presley", "Howlin' Wolf", "LaVern Baker", "Otis Spann", "Ray Charles", "Robert Johnson", "Slim Harpo", "Solomon Burke", "T-Bone Walker"], "followers": ["Bob Seger", "Bruce Springsteen", "David Johansen", "Deep Purple", "Elvis Costello", "Grand Funk Railroad", "Humble Pie", "Iron Butterfly", "Joe Cocker", "MC5", "Omar & the Howlers", "The Hives", "The Vines", "Tom Petty"]}